swirl/__init__.py
swirl/cluster.py
swirl/evcmap.py
swirl/main.py
swirl/plots.py
swirl/rortex.py
swirl/swirlingstrength.py
swirl/utils.py
swirl/vortex.py
swirl/vorticity.py
swirl_code-1.0.2.dist-info/LICENSE.txt
swirl_code-1.0.2.dist-info/METADATA
swirl_code-1.0.2.dist-info/WHEEL
swirl_code-1.0.2.dist-info/top_level.txt
swirl_code-1.0.2.dist-info/RECORD
