Metadata-Version: 2.1
Name: swirl-code
Version: 1.0.2
Summary: The SWirl Identification by Rotation centers Localization (SWIRL) is an automated vortex identification algorithm written in python and based on the _Estimated Vortex Center_ (EVC) method [Canivete Cuissa & Steiner, 2022]. Given a two-dimensional velocity field defined on a Cartesian grid and the grid cell size in physical units, the SWIRL code returns a list with the identified vortical structures and their main properties.
Author-email: José Roberto Canivete Cuissa <jose.canivete@irsol.usi.ch>
License: MIT
Project-URL: Documentation, https://github.com/jcanivete/swirl/blob/main/README.md
Project-URL: Issues, https://github.com/jcanivete/swirl/issues
Project-URL: Source, https://github.com/jcanivete/swirl
Keywords: vortex,fluid dynamics,physics,simulation
Classifier: Development Status :: 4 - Beta
Classifier: Programming Language :: Python
Classifier: Programming Language :: Python :: 3.8
Classifier: Programming Language :: Python :: 3.9
Classifier: Programming Language :: Python :: 3.10
Classifier: Programming Language :: Python :: 3.11
Classifier: Programming Language :: Python :: 3.12
Classifier: Programming Language :: Python :: Implementation :: CPython
Classifier: Programming Language :: Python :: Implementation :: PyPy
Classifier: Operating System :: OS Independent
Classifier: Intended Audience :: Science/Research
Classifier: Topic :: Scientific/Engineering :: Physics
Requires-Python: >=3.10
License-File: LICENSE.txt
Requires-Dist: numpy >=1.21.6
Requires-Dist: scipy >=1.4.1
Requires-Dist: matplotlib >=3.3.2
Requires-Dist: h5py >=2.10.0
